datatricks/__init__.py
datatricks-0.1.0.dist-info/WHEEL
datatricks-0.1.0.dist-info/METADATA
datatricks-0.1.0.dist-info/RECORD
